sacp/__init__.py
sacp/base.py
sacp/node.py
sacp/utilities.py
sacp-0.7.0.dist-info/LICENSE
sacp-0.7.0.dist-info/METADATA
sacp-0.7.0.dist-info/WHEEL
sacp-0.7.0.dist-info/top_level.txt
sacp-0.7.0.dist-info/RECORD
