Metadata-Version: 2.1
Name: sacp
Version: 0.7.0
Summary: A simple Apache Config Parser
Home-page: https://github.com/catatonicprime/sacp
Author: catatonicprime
Author-email: catatonicprime@gmail.com
License: UNKNOWN
Platform: UNKNOWN
Classifier: Programming Language :: Python :: 3
Classifier: License :: OSI Approved :: MIT License
Classifier: Operating System :: OS Independent
Requires-Dist: pygments (>=2.8.1)
